dssim/__init__.py
dssim/pubsub.py
dssim/simulation.py
dssim/timequeue.py
dssim/utils.py
dssim/components/__init__.py
dssim/components/clock.py
dssim/components/delay.py
dssim/components/event.py
dssim/components/i2c.py
dssim/components/limiter.py
dssim/components/queue.py
dssim/components/uart.py
tests/__init__.py
tests/test_event.py
tests/test_interface.py
tests/test_pubsub.py
tests/test_queue.py
tests/test_simulation.py
tests/test_timequeue.py
dssim-0.4.dist-info/LICENSE
dssim-0.4.dist-info/METADATA
dssim-0.4.dist-info/NOTICE
dssim-0.4.dist-info/WHEEL
dssim-0.4.dist-info/top_level.txt
dssim-0.4.dist-info/RECORD
