Metadata-Version: 2.1
Name: dssim
Version: 0.4
Summary: Discrete System Simulation framework
Home-page: https://github.com/majvan/dssim
Author: NXP Semiconductors
Author-email: juraj.vanco@nxp.com
License: apache-2.0
Keywords: simulation,simulator,discrete,system,event,Process,event-based,time
Platform: UNKNOWN
Classifier: Development Status :: 3 - Alpha
Classifier: Intended Audience :: Developers
Classifier: Topic :: Software Development
Classifier: License :: OSI Approved :: Apache Software License
Classifier: Programming Language :: Python :: 3
License-File: LICENSE
License-File: NOTICE
